<?xml version='1.0' encoding='utf-8'?>
<list>
	<config showall="true" notax="true" />
	<item>
		<ingredient id="57" count="14098000"/>
		<production id="5609" count="1"/>
	</item>
	<item>
		<ingredient id="57" count="14098000"/>
		<production id="5608" count="1"/>
	</item>
	<item>
		<ingredient id="57" count="14098000"/>
		<production id="5610" count="1"/>
	</item>
	<item>
		<ingredient id="57" count="26968400"/>
		<production id="5613" count="1"/>
	</item>
	<item>
		<ingredient id="57" count="20741000"/>
		<production id="5611" count="1"/>
	</item>
	<item>
		<ingredient id="57" count="26968400"/>
		<production id="5612" count="1"/>
	</item>
	<item>
		<ingredient id="57" count="26968400"/>
		<production id="8806" count="1"/>
	</item>
	<item>
		<ingredient id="57" count="26968400"/>
		<production id="8807" count="1"/>
	</item>
	<item>
		<ingredient id="57" count="26968400"/>
		<production id="8808" count="1"/>
	</item>
</list>