<?xml version="1.0" encoding="UTF-8"?>

<list>
	<etcitem id="7904" name="Boat Ticket: Rune to Gludin" type="OTHER">
		<!--Done By Ragnarok (c)L2Open-Team-->
		<!--LastChange: 10.01.2011-23:26-->
		<set name="icon" val="icon.etc_ticket_red_i00" />
		<set name="weight" val="20" />
		<set name="stackable" val="true" />
		<set name="price" val="5000" />
	</etcitem>
	<etcitem id="7905" name="Boat Ticket: Gludin to Rune" type="OTHER">
		<!--Done By Ragnarok (c)L2Open-Team-->
		<!--LastChange: 10.01.2011-23:26-->
		<set name="icon" val="icon.etc_ticket_red_i00" />
		<set name="weight" val="20" />
		<set name="stackable" val="true" />
		<set name="price" val="5000" />
	</etcitem>
	<etcitem id="7906" name="Blessing of Fire" type="OTHER">
		<!--Done By Ragnarok (c)L2Open-Team-->
		<!--LastChange: 10.01.2011-23:26-->
		<set name="icon" val="icon.etc_fire_crystal_1_i00" />
		<set name="weight" val="20" />
		<set name="stackable" val="true" />
		<set name="price" val="2000" />
		<skills>
			<skill id="2248" lvl="1" />
		</skills>
	</etcitem>
	<etcitem id="7907" name="Blessing of Water" type="OTHER">
		<!--Done By Ragnarok (c)L2Open-Team-->
		<!--LastChange: 10.01.2011-23:26-->
		<set name="icon" val="icon.etc_water_crystal_1_i00" />
		<set name="weight" val="20" />
		<set name="stackable" val="true" />
		<set name="price" val="2000" />
		<skills>
			<skill id="2249" lvl="1" />
		</skills>
	</etcitem>
	<etcitem id="7908" name="Blessing of Wind" type="OTHER">
		<!--Done By Ragnarok (c)L2Open-Team-->
		<!--LastChange: 10.01.2011-23:26-->
		<set name="icon" val="icon.etc_wind_crystal_1_i00" />
		<set name="weight" val="20" />
		<set name="stackable" val="true" />
		<set name="price" val="2000" />
		<skills>
			<skill id="2250" lvl="1" />
		</skills>
	</etcitem>
	<etcitem id="7909" name="Blessing of Earth" type="OTHER">
		<!--Done By Ragnarok (c)L2Open-Team-->
		<!--LastChange: 10.01.2011-23:26-->
		<set name="icon" val="icon.etc_earth_crystal_1_i00" />
		<set name="weight" val="20" />
		<set name="stackable" val="true" />
		<set name="price" val="2000" />
		<skills>
			<skill id="2251" lvl="1" />
		</skills>
	</etcitem>
	<etcitem id="7910" name="Blessing of Darkness" type="OTHER">
		<!--Done By Ragnarok (c)L2Open-Team-->
		<!--LastChange: 10.01.2011-23:26-->
		<set name="icon" val="icon.etc_unholy_crystal_1_i00" />
		<set name="weight" val="20" />
		<set name="stackable" val="true" />
		<set name="price" val="5000" />
		<skills>
			<skill id="2252" lvl="1" />
		</skills>
	</etcitem>
	<etcitem id="7911" name="Blessing of Sanctity" type="OTHER">
		<!--Done By Ragnarok (c)L2Open-Team-->
		<!--LastChange: 10.01.2011-23:26-->
		<set name="icon" val="icon.etc_holy_crystal_1_i00" />
		<set name="weight" val="20" />
		<set name="stackable" val="true" />
		<set name="price" val="5000" />
		<skills>
			<skill id="2253" lvl="1" />
		</skills>
	</etcitem>
	<etcitem id="7912" name="Fire Crystal" type="OTHER">
		<!--Done By Ragnarok (c)L2Open-Team-->
		<!--LastChange: 10.01.2011-23:26-->
		<set name="icon" val="icon.etc_fire_crystal_1_i00" />
		<set name="weight" val="20" />
		<set name="stackable" val="true" />
		<set name="price" val="2000" />
		<skills>
			<skill id="2254" lvl="1" />
		</skills>
	</etcitem>
	<etcitem id="7913" name="Water Crystal" type="OTHER">
		<!--Done By Ragnarok (c)L2Open-Team-->
		<!--LastChange: 10.01.2011-23:26-->
		<set name="icon" val="icon.etc_water_crystal_1_i00" />
		<set name="weight" val="20" />
		<set name="stackable" val="true" />
		<set name="price" val="2000" />
		<skills>
			<skill id="2255" lvl="1" />
		</skills>
	</etcitem>
	<etcitem id="7914" name="Wind Crystal" type="OTHER">
		<!--Done By Ragnarok (c)L2Open-Team-->
		<!--LastChange: 10.01.2011-23:26-->
		<set name="icon" val="icon.etc_wind_crystal_1_i00" />
		<set name="weight" val="20" />
		<set name="stackable" val="true" />
		<set name="price" val="2000" />
		<skills>
			<skill id="2256" lvl="1" />
		</skills>
	</etcitem>
	<etcitem id="7915" name="Earth Crystal" type="OTHER">
		<!--Done By Ragnarok (c)L2Open-Team-->
		<!--LastChange: 10.01.2011-23:26-->
		<set name="icon" val="icon.etc_earth_crystal_1_i00" />
		<set name="weight" val="20" />
		<set name="stackable" val="true" />
		<set name="price" val="2000" />
		<skills>
			<skill id="2257" lvl="1" />
		</skills>
	</etcitem>
	<etcitem id="7916" name="Dark Shard" type="OTHER">
		<!--Done By Ragnarok (c)L2Open-Team-->
		<!--LastChange: 10.01.2011-23:26-->
		<set name="icon" val="icon.etc_unholy_crystal_1_i00" />
		<set name="weight" val="20" />
		<set name="stackable" val="true" />
		<set name="price" val="3000" />
		<skills>
			<skill id="2258" lvl="1" />
		</skills>
	</etcitem>
	<etcitem id="7917" name="Sanctity Crystal" type="OTHER">
		<!--Done By Ragnarok (c)L2Open-Team-->
		<!--LastChange: 10.01.2011-23:26-->
		<set name="icon" val="icon.etc_holy_crystal_1_i00" />
		<set name="weight" val="20" />
		<set name="stackable" val="true" />
		<set name="price" val="3000" />
		<skills>
			<skill id="2259" lvl="1" />
		</skills>
	</etcitem>
	<etcitem id="7918" name="Mercenary Posting Ticket (Sword/Stationary)" type="SCROLL">
		<!--Done By Ragnarok (c)L2Open-Team-->
		<!--LastChange: 10.01.2011-23:26-->
		<set name="icon" val="icon.mticket_sword_fix_i00" />
		<set name="stackable" val="true" />
		<set name="tradeable" val="false" />
		<set name="price" val="50000" />
		<set name="dropable" val="false" />
	</etcitem>
	<etcitem id="7919" name="Mercenary Posting Ticket (Spear/Stationary)" type="SCROLL">
		<!--Done By Ragnarok (c)L2Open-Team-->
		<!--LastChange: 10.01.2011-23:26-->
		<set name="icon" val="icon.mticket_pole_fix_i00" />
		<set name="stackable" val="true" />
		<set name="tradeable" val="false" />
		<set name="price" val="60000" />
		<set name="dropable" val="false" />
	</etcitem>
	<etcitem id="7920" name="Mercenary Posting Ticket (Bow/Stationary)" type="SCROLL">
		<!--Done By Ragnarok (c)L2Open-Team-->
		<!--LastChange: 10.01.2011-23:26-->
		<set name="icon" val="icon.mticket_bow_fix_i00" />
		<set name="stackable" val="true" />
		<set name="tradeable" val="false" />
		<set name="price" val="70000" />
		<set name="dropable" val="false" />
	</etcitem>
	<etcitem id="7921" name="Mercenary Posting Ticket (Cleric/Stationary)" type="SCROLL">
		<!--Done By Ragnarok (c)L2Open-Team-->
		<!--LastChange: 10.01.2011-23:26-->
		<set name="icon" val="icon.mticket_cleric_fix_i00" />
		<set name="stackable" val="true" />
		<set name="tradeable" val="false" />
		<set name="price" val="170000" />
		<set name="dropable" val="false" />
	</etcitem>
	<etcitem id="7922" name="Mercenary Posting Ticket (Wizard/Stationary)" type="SCROLL">
		<!--Done By Ragnarok (c)L2Open-Team-->
		<!--LastChange: 10.01.2011-23:26-->
		<set name="icon" val="icon.mticket_wizard_fix_i00" />
		<set name="stackable" val="true" />
		<set name="tradeable" val="false" />
		<set name="price" val="170000" />
		<set name="dropable" val="false" />
	</etcitem>
	<etcitem id="7923" name="Mercenary Posting Ticket (Sword/Mobile)" type="SCROLL">
		<!--Done By Ragnarok (c)L2Open-Team-->
		<!--LastChange: 10.01.2011-23:26-->
		<set name="icon" val="icon.mticket_sword_move_i00" />
		<set name="stackable" val="true" />
		<set name="tradeable" val="false" />
		<set name="price" val="50000" />
		<set name="dropable" val="false" />
	</etcitem>
	<etcitem id="7924" name="Mercenary Posting Ticket (Spear/Mobile)" type="SCROLL">
		<!--Done By Ragnarok (c)L2Open-Team-->
		<!--LastChange: 10.01.2011-23:26-->
		<set name="icon" val="icon.mticket_pole_move_i00" />
		<set name="stackable" val="true" />
		<set name="tradeable" val="false" />
		<set name="price" val="60000" />
		<set name="dropable" val="false" />
	</etcitem>
	<etcitem id="7925" name="Mercenary Posting Ticket (Bow/Mobile)" type="SCROLL">
		<!--Done By Ragnarok (c)L2Open-Team-->
		<!--LastChange: 10.01.2011-23:26-->
		<set name="icon" val="icon.mticket_bow_move_i00" />
		<set name="stackable" val="true" />
		<set name="tradeable" val="false" />
		<set name="price" val="70000" />
		<set name="dropable" val="false" />
	</etcitem>
	<etcitem id="7926" name="Mercenary Posting Ticket (Cleric/Mobile)" type="SCROLL">
		<!--Done By Ragnarok (c)L2Open-Team-->
		<!--LastChange: 10.01.2011-23:26-->
		<set name="icon" val="icon.mticket_cleric_move_i00" />
		<set name="stackable" val="true" />
		<set name="tradeable" val="false" />
		<set name="price" val="170000" />
		<set name="dropable" val="false" />
	</etcitem>
	<etcitem id="7927" name="Mercenary Posting Ticket (Wizard/Mobile)" type="SCROLL">
		<!--Done By Ragnarok (c)L2Open-Team-->
		<!--LastChange: 10.01.2011-23:26-->
		<set name="icon" val="icon.mticket_wizard_move_i00" />
		<set name="stackable" val="true" />
		<set name="tradeable" val="false" />
		<set name="price" val="170000" />
		<set name="dropable" val="false" />
	</etcitem>
	<etcitem id="7928" name="Mercenary Posting Ticket (Teleporter1)" type="SCROLL">
		<!--Done By Ragnarok (c)L2Open-Team-->
		<!--LastChange: 10.01.2011-23:26-->
		<set name="icon" val="icon.mticket_teleporter_fix_i00" />
		<set name="stackable" val="true" />
		<set name="tradeable" val="false" />
		<set name="price" val="100000" />
		<set name="dropable" val="false" />
	</etcitem>
	<etcitem id="7929" name="Mercenary Posting Ticket (Teleporter2)" type="SCROLL">
		<!--Done By Ragnarok (c)L2Open-Team-->
		<!--LastChange: 10.01.2011-23:26-->
		<set name="icon" val="icon.mticket_teleporter_fix_i00" />
		<set name="stackable" val="true" />
		<set name="tradeable" val="false" />
		<set name="price" val="100000" />
		<set name="dropable" val="false" />
	</etcitem>
	<etcitem id="7930" name="Mercenary Posting Ticket (Teleporter3)" type="SCROLL">
		<!--Done By Ragnarok (c)L2Open-Team-->
		<!--LastChange: 10.01.2011-23:26-->
		<set name="icon" val="icon.mticket_teleporter_fix_i00" />
		<set name="stackable" val="true" />
		<set name="tradeable" val="false" />
		<set name="price" val="100000" />
		<set name="dropable" val="false" />
	</etcitem>
	<etcitem id="7931" name="Greater Mercenary Posting Ticket (Sword/Stationary)" type="SCROLL">
		<!--Done By Ragnarok (c)L2Open-Team-->
		<!--LastChange: 10.01.2011-23:26-->
		<set name="icon" val="icon.mticket_sword_fix_i00" />
		<set name="stackable" val="true" />
		<set name="tradeable" val="false" />
		<set name="price" val="80000" />
		<set name="dropable" val="false" />
	</etcitem>
	<etcitem id="7932" name="Greater Mercenary Posting Ticket (Spear/Stationary)" type="SCROLL">
		<!--Done By Ragnarok (c)L2Open-Team-->
		<!--LastChange: 10.01.2011-23:26-->
		<set name="icon" val="icon.mticket_pole_fix_i00" />
		<set name="stackable" val="true" />
		<set name="tradeable" val="false" />
		<set name="price" val="100000" />
		<set name="dropable" val="false" />
	</etcitem>
	<etcitem id="7933" name="Greater Mercenary Posting Ticket (Bow/Stationary)" type="SCROLL">
		<!--Done By Ragnarok (c)L2Open-Team-->
		<!--LastChange: 10.01.2011-23:26-->
		<set name="icon" val="icon.mticket_bow_fix_i00" />
		<set name="stackable" val="true" />
		<set name="tradeable" val="false" />
		<set name="price" val="120000" />
		<set name="dropable" val="false" />
	</etcitem>
	<etcitem id="7934" name="Greater Mercenary Posting Ticket (Cleric/Stationary)" type="SCROLL">
		<!--Done By Ragnarok (c)L2Open-Team-->
		<!--LastChange: 10.01.2011-23:26-->
		<set name="icon" val="icon.mticket_cleric_fix_i00" />
		<set name="stackable" val="true" />
		<set name="tradeable" val="false" />
		<set name="price" val="250000" />
		<set name="dropable" val="false" />
	</etcitem>
	<etcitem id="7935" name="Greater Mercenary Posting Ticket (Wizard/Stationary)" type="SCROLL">
		<!--Done By Ragnarok (c)L2Open-Team-->
		<!--LastChange: 10.01.2011-23:26-->
		<set name="icon" val="icon.mticket_wizard_fix_i00" />
		<set name="stackable" val="true" />
		<set name="tradeable" val="false" />
		<set name="price" val="250000" />
		<set name="dropable" val="false" />
	</etcitem>
	<etcitem id="7936" name="Greater Mercenary Posting Ticket (Sword/Mobile)" type="SCROLL">
		<!--Done By Ragnarok (c)L2Open-Team-->
		<!--LastChange: 10.01.2011-23:26-->
		<set name="icon" val="icon.mticket_sword_move_i00" />
		<set name="stackable" val="true" />
		<set name="tradeable" val="false" />
		<set name="price" val="80000" />
		<set name="dropable" val="false" />
	</etcitem>
	<etcitem id="7937" name="Greater Mercenary Posting Ticket (Spear/Mobile)" type="SCROLL">
		<!--Done By Ragnarok (c)L2Open-Team-->
		<!--LastChange: 10.01.2011-23:26-->
		<set name="icon" val="icon.mticket_pole_move_i00" />
		<set name="stackable" val="true" />
		<set name="tradeable" val="false" />
		<set name="price" val="100000" />
		<set name="dropable" val="false" />
	</etcitem>
	<etcitem id="7938" name="Greater Mercenary Posting Ticket (Bow/Mobile)" type="SCROLL">
		<!--Done By Ragnarok (c)L2Open-Team-->
		<!--LastChange: 10.01.2011-23:26-->
		<set name="icon" val="icon.mticket_bow_move_i00" />
		<set name="stackable" val="true" />
		<set name="tradeable" val="false" />
		<set name="price" val="120000" />
		<set name="dropable" val="false" />
	</etcitem>
	<etcitem id="7939" name="Greater Mercenary Posting Ticket (Cleric/Mobile)" type="SCROLL">
		<!--Done By Ragnarok (c)L2Open-Team-->
		<!--LastChange: 10.01.2011-23:26-->
		<set name="icon" val="icon.mticket_cleric_move_i00" />
		<set name="stackable" val="true" />
		<set name="tradeable" val="false" />
		<set name="price" val="250000" />
		<set name="dropable" val="false" />
	</etcitem>
	<etcitem id="7940" name="Greater Mercenary Posting Ticket (Wizard/Mobile)" type="SCROLL">
		<!--Done By Ragnarok (c)L2Open-Team-->
		<!--LastChange: 10.01.2011-23:26-->
		<set name="icon" val="icon.mticket_wizard_move_i00" />
		<set name="stackable" val="true" />
		<set name="tradeable" val="false" />
		<set name="price" val="250000" />
		<set name="dropable" val="false" />
	</etcitem>
	<etcitem id="7941" name="Dawn Mercenary Posting Ticket (Sword/Stationary)" type="SCROLL">
		<!--Done By Ragnarok (c)L2Open-Team-->
		<!--LastChange: 10.01.2011-23:26-->
		<set name="icon" val="icon.mticket_sword_fix_i00" />
		<set name="stackable" val="true" />
		<set name="tradeable" val="false" />
		<set name="price" val="140000" />
		<set name="dropable" val="false" />
	</etcitem>
	<etcitem id="7942" name="Dawn Mercenary Posting Ticket (Spear/Stationary)" type="SCROLL">
		<!--Done By Ragnarok (c)L2Open-Team-->
		<!--LastChange: 10.01.2011-23:26-->
		<set name="icon" val="icon.mticket_pole_fix_i00" />
		<set name="stackable" val="true" />
		<set name="tradeable" val="false" />
		<set name="price" val="170000" />
		<set name="dropable" val="false" />
	</etcitem>
	<etcitem id="7943" name="Dawn Mercenary Posting Ticket (Bow/Stationary)" type="SCROLL">
		<!--Done By Ragnarok (c)L2Open-Team-->
		<!--LastChange: 10.01.2011-23:26-->
		<set name="icon" val="icon.mticket_bow_fix_i00" />
		<set name="stackable" val="true" />
		<set name="tradeable" val="false" />
		<set name="price" val="200000" />
		<set name="dropable" val="false" />
	</etcitem>
	<etcitem id="7944" name="Dawn Mercenary Posting Ticket (Cleric/Stationary)" type="SCROLL">
		<!--Done By Ragnarok (c)L2Open-Team-->
		<!--LastChange: 10.01.2011-23:26-->
		<set name="icon" val="icon.mticket_cleric_fix_i00" />
		<set name="stackable" val="true" />
		<set name="tradeable" val="false" />
		<set name="price" val="350000" />
		<set name="dropable" val="false" />
	</etcitem>
	<etcitem id="7945" name="Dawn Mercenary Posting Ticket (Wizard/Stationary)" type="SCROLL">
		<!--Done By Ragnarok (c)L2Open-Team-->
		<!--LastChange: 10.01.2011-23:26-->
		<set name="icon" val="icon.mticket_wizard_fix_i00" />
		<set name="stackable" val="true" />
		<set name="tradeable" val="false" />
		<set name="price" val="350000" />
		<set name="dropable" val="false" />
	</etcitem>
	<etcitem id="7946" name="Dawn Mercenary Posting Ticket (Sword/Mobile)" type="SCROLL">
		<!--Done By Ragnarok (c)L2Open-Team-->
		<!--LastChange: 10.01.2011-23:26-->
		<set name="icon" val="icon.mticket_sword_move_i00" />
		<set name="stackable" val="true" />
		<set name="tradeable" val="false" />
		<set name="price" val="140000" />
		<set name="dropable" val="false" />
	</etcitem>
	<etcitem id="7947" name="Dawn Mercenary Posting Ticket (Spear/Mobile)" type="SCROLL">
		<!--Done By Ragnarok (c)L2Open-Team-->
		<!--LastChange: 10.01.2011-23:26-->
		<set name="icon" val="icon.mticket_pole_move_i00" />
		<set name="stackable" val="true" />
		<set name="tradeable" val="false" />
		<set name="price" val="170000" />
		<set name="dropable" val="false" />
	</etcitem>
	<etcitem id="7948" name="Dawn Mercenary Posting Ticket (Bow/Mobile)" type="SCROLL">
		<!--Done By Ragnarok (c)L2Open-Team-->
		<!--LastChange: 10.01.2011-23:26-->
		<set name="icon" val="icon.mticket_bow_move_i00" />
		<set name="stackable" val="true" />
		<set name="tradeable" val="false" />
		<set name="price" val="200000" />
		<set name="dropable" val="false" />
	</etcitem>
	<etcitem id="7949" name="Dawn Mercenary Posting Ticket (Cleric/Mobile)" type="SCROLL">
		<!--Done By Ragnarok (c)L2Open-Team-->
		<!--LastChange: 10.01.2011-23:26-->
		<set name="icon" val="icon.mticket_cleric_move_i00" />
		<set name="stackable" val="true" />
		<set name="tradeable" val="false" />
		<set name="price" val="350000" />
		<set name="dropable" val="false" />
	</etcitem>
	<etcitem id="7950" name="Dawn Mercenary Posting Ticket (Wizard/Mobile)" type="SCROLL">
		<!--Done By Ragnarok (c)L2Open-Team-->
		<!--LastChange: 10.01.2011-23:26-->
		<set name="icon" val="icon.mticket_wizard_move_i00" />
		<set name="stackable" val="true" />
		<set name="tradeable" val="false" />
		<set name="price" val="350000" />
		<set name="dropable" val="false" />
	</etcitem>
	<etcitem id="7951" name="Greater Recruit Posting Ticket (Sword/Stationary)" type="SCROLL">
		<!--Done By Ragnarok (c)L2Open-Team-->
		<!--LastChange: 10.01.2011-23:26-->
		<set name="icon" val="icon.mticket_sword_fix_i00" />
		<set name="stackable" val="true" />
		<set name="tradeable" val="false" />
		<set name="price" val="70000" />
		<set name="dropable" val="false" />
	</etcitem>
	<etcitem id="7952" name="Greater Recruit Posting Ticket (Spear/Stationary)" type="SCROLL">
		<!--Done By Ragnarok (c)L2Open-Team-->
		<!--LastChange: 10.01.2011-23:26-->
		<set name="icon" val="icon.mticket_pole_fix_i00" />
		<set name="stackable" val="true" />
		<set name="tradeable" val="false" />
		<set name="price" val="90000" />
		<set name="dropable" val="false" />
	</etcitem>
	<etcitem id="7953" name="Greater Recruit Posting Ticket (Bow/Stationary)" type="SCROLL">
		<!--Done By Ragnarok (c)L2Open-Team-->
		<!--LastChange: 10.01.2011-23:26-->
		<set name="icon" val="icon.mticket_bow_fix_i00" />
		<set name="stackable" val="true" />
		<set name="tradeable" val="false" />
		<set name="price" val="110000" />
		<set name="dropable" val="false" />
	</etcitem>
	<etcitem id="7954" name="Greater Recruit Posting Ticket (Cleric/Stationary)" type="SCROLL">
		<!--Done By Ragnarok (c)L2Open-Team-->
		<!--LastChange: 10.01.2011-23:26-->
		<set name="icon" val="icon.mticket_cleric_fix_i00" />
		<set name="stackable" val="true" />
		<set name="tradeable" val="false" />
		<set name="price" val="230000" />
		<set name="dropable" val="false" />
	</etcitem>
	<etcitem id="7955" name="Greater Recruit Posting Ticket (Wizard/Stationary)" type="SCROLL">
		<!--Done By Ragnarok (c)L2Open-Team-->
		<!--LastChange: 10.01.2011-23:26-->
		<set name="icon" val="icon.mticket_wizard_fix_i00" />
		<set name="stackable" val="true" />
		<set name="tradeable" val="false" />
		<set name="price" val="230000" />
		<set name="dropable" val="false" />
	</etcitem>
	<etcitem id="7956" name="Greater Recruit Posting Ticket (Sword/Mobile)" type="SCROLL">
		<!--Done By Ragnarok (c)L2Open-Team-->
		<!--LastChange: 10.01.2011-23:26-->
		<set name="icon" val="icon.mticket_sword_move_i00" />
		<set name="stackable" val="true" />
		<set name="tradeable" val="false" />
		<set name="price" val="70000" />
		<set name="dropable" val="false" />
	</etcitem>
	<etcitem id="7957" name="Greater Recruit Posting Ticket (Spear/Mobile)" type="SCROLL">
		<!--Done By Ragnarok (c)L2Open-Team-->
		<!--LastChange: 10.01.2011-23:26-->
		<set name="icon" val="icon.mticket_pole_move_i00" />
		<set name="stackable" val="true" />
		<set name="tradeable" val="false" />
		<set name="price" val="90000" />
		<set name="dropable" val="false" />
	</etcitem>
	<etcitem id="7958" name="Greater Recruit Posting Ticket (Bow/Mobile)" type="SCROLL">
		<!--Done By Ragnarok (c)L2Open-Team-->
		<!--LastChange: 10.01.2011-23:26-->
		<set name="icon" val="icon.mticket_bow_move_i00" />
		<set name="stackable" val="true" />
		<set name="tradeable" val="false" />
		<set name="price" val="110000" />
		<set name="dropable" val="false" />
	</etcitem>
	<etcitem id="7959" name="Greater Recruit Posting Ticket (Cleric/Mobile)" type="SCROLL">
		<!--Done By Ragnarok (c)L2Open-Team-->
		<!--LastChange: 10.01.2011-23:26-->
		<set name="icon" val="icon.mticket_cleric_move_i00" />
		<set name="stackable" val="true" />
		<set name="tradeable" val="false" />
		<set name="price" val="230000" />
		<set name="dropable" val="false" />
	</etcitem>
	<etcitem id="7960" name="Greater Recruit Posting Ticket (Wizard/Mobile)" type="SCROLL">
		<!--Done By Ragnarok (c)L2Open-Team-->
		<!--LastChange: 10.01.2011-23:26-->
		<set name="icon" val="icon.mticket_wizard_move_i00" />
		<set name="stackable" val="true" />
		<set name="tradeable" val="false" />
		<set name="price" val="230000" />
		<set name="dropable" val="false" />
	</etcitem>
	<etcitem id="7961" name="Recruit Posting Ticket (Sword/Stationary)" type="SCROLL">
		<!--Done By Ragnarok (c)L2Open-Team-->
		<!--LastChange: 10.01.2011-23:26-->
		<set name="icon" val="icon.mticket_sword_fix_i00" />
		<set name="stackable" val="true" />
		<set name="tradeable" val="false" />
		<set name="price" val="40000" />
		<set name="dropable" val="false" />
	</etcitem>
	<etcitem id="7962" name="Recruit Posting Ticket (Spear/Stationary)" type="SCROLL">
		<!--Done By Ragnarok (c)L2Open-Team-->
		<!--LastChange: 10.01.2011-23:26-->
		<set name="icon" val="icon.mticket_pole_fix_i00" />
		<set name="stackable" val="true" />
		<set name="tradeable" val="false" />
		<set name="price" val="50000" />
		<set name="dropable" val="false" />
	</etcitem>
	<etcitem id="7963" name="Recruit Posting Ticket (Bow/Stationary)" type="SCROLL">
		<!--Done By Ragnarok (c)L2Open-Team-->
		<!--LastChange: 10.01.2011-23:26-->
		<set name="icon" val="icon.mticket_bow_fix_i00" />
		<set name="stackable" val="true" />
		<set name="tradeable" val="false" />
		<set name="price" val="60000" />
		<set name="dropable" val="false" />
	</etcitem>
	<etcitem id="7964" name="Recruit Posting Ticket (Cleric/Stationary)" type="SCROLL">
		<!--Done By Ragnarok (c)L2Open-Team-->
		<!--LastChange: 10.01.2011-23:26-->
		<set name="icon" val="icon.mticket_cleric_fix_i00" />
		<set name="stackable" val="true" />
		<set name="tradeable" val="false" />
		<set name="price" val="150000" />
		<set name="dropable" val="false" />
	</etcitem>
	<etcitem id="7965" name="Recruit Posting Ticket (Wizard/Stationary)" type="SCROLL">
		<!--Done By Ragnarok (c)L2Open-Team-->
		<!--LastChange: 10.01.2011-23:26-->
		<set name="icon" val="icon.mticket_wizard_fix_i00" />
		<set name="stackable" val="true" />
		<set name="tradeable" val="false" />
		<set name="price" val="150000" />
		<set name="dropable" val="false" />
	</etcitem>
	<etcitem id="7966" name="Recruit Posting Ticket (Sword/Mobile)" type="SCROLL">
		<!--Done By Ragnarok (c)L2Open-Team-->
		<!--LastChange: 10.01.2011-23:26-->
		<set name="icon" val="icon.mticket_sword_move_i00" />
		<set name="stackable" val="true" />
		<set name="tradeable" val="false" />
		<set name="price" val="40000" />
		<set name="dropable" val="false" />
	</etcitem>
	<etcitem id="7967" name="Recruit Posting Ticket (Spear/Mobile)" type="SCROLL">
		<!--Done By Ragnarok (c)L2Open-Team-->
		<!--LastChange: 10.01.2011-23:26-->
		<set name="icon" val="icon.mticket_pole_move_i00" />
		<set name="stackable" val="true" />
		<set name="tradeable" val="false" />
		<set name="price" val="50000" />
		<set name="dropable" val="false" />
	</etcitem>
	<etcitem id="7968" name="Recruit Posting Ticket (Bow/Mobile)" type="SCROLL">
		<!--Done By Ragnarok (c)L2Open-Team-->
		<!--LastChange: 10.01.2011-23:26-->
		<set name="icon" val="icon.mticket_bow_move_i00" />
		<set name="stackable" val="true" />
		<set name="tradeable" val="false" />
		<set name="price" val="60000" />
		<set name="dropable" val="false" />
	</etcitem>
	<etcitem id="7969" name="Recruit Posting Ticket (Cleric/Mobile)" type="SCROLL">
		<!--Done By Ragnarok (c)L2Open-Team-->
		<!--LastChange: 10.01.2011-23:26-->
		<set name="icon" val="icon.mticket_cleric_move_i00" />
		<set name="stackable" val="true" />
		<set name="tradeable" val="false" />
		<set name="price" val="150000" />
		<set name="dropable" val="false" />
	</etcitem>
	<etcitem id="7970" name="Recruit Posting Ticket (Wizard/Mobile)" type="SCROLL">
		<!--Done By Ragnarok (c)L2Open-Team-->
		<!--LastChange: 10.01.2011-23:26-->
		<set name="icon" val="icon.mticket_wizard_move_i00" />
		<set name="stackable" val="true" />
		<set name="tradeable" val="false" />
		<set name="price" val="150000" />
		<set name="dropable" val="false" />
	</etcitem>
	<etcitem id="7971" name="Nephilim Warrior Posting Ticket" type="SCROLL">
		<!--Done By Ragnarok (c)L2Open-Team-->
		<!--LastChange: 10.01.2011-23:26-->
		<set name="icon" val="icon.mticket_sword_move_i00" />
		<set name="stackable" val="true" />
		<set name="tradeable" val="false" />
		<set name="price" val="2500000" />
		<set name="dropable" val="false" />
	</etcitem>
	<etcitem id="7972" name="Nephilim Shaman Posting Ticket" type="SCROLL">
		<!--Done By Ragnarok (c)L2Open-Team-->
		<!--LastChange: 10.01.2011-23:26-->
		<set name="icon" val="icon.mticket_wizard_move_i00" />
		<set name="stackable" val="true" />
		<set name="tradeable" val="false" />
		<set name="price" val="5000000" />
		<set name="dropable" val="false" />
	</etcitem>
	<etcitem id="7973" name="Mercenary Posting Ticket (Sword/Stationary)" type="SCROLL">
		<!--Done By Ragnarok (c)L2Open-Team-->
		<!--LastChange: 10.01.2011-23:26-->
		<set name="icon" val="icon.mticket_sword_fix_i00" />
		<set name="stackable" val="true" />
		<set name="price" val="50000" />
	</etcitem>
	<etcitem id="7974" name="Mercenary Posting Ticket (Spear/Stationary)" type="SCROLL">
		<!--Done By Ragnarok (c)L2Open-Team-->
		<!--LastChange: 10.01.2011-23:26-->
		<set name="icon" val="icon.mticket_pole_fix_i00" />
		<set name="stackable" val="true" />
		<set name="tradeable" val="false" />
		<set name="price" val="60000" />
		<set name="dropable" val="false" />
	</etcitem>
	<etcitem id="7975" name="Mercenary Posting Ticket (Bow/Stationary)" type="SCROLL">
		<!--Done By Ragnarok (c)L2Open-Team-->
		<!--LastChange: 10.01.2011-23:26-->
		<set name="icon" val="icon.mticket_bow_fix_i00" />
		<set name="stackable" val="true" />
		<set name="tradeable" val="false" />
		<set name="price" val="70000" />
		<set name="dropable" val="false" />
	</etcitem>
	<etcitem id="7976" name="Mercenary Posting Ticket (Cleric/Stationary)" type="SCROLL">
		<!--Done By Ragnarok (c)L2Open-Team-->
		<!--LastChange: 10.01.2011-23:26-->
		<set name="icon" val="icon.mticket_cleric_fix_i00" />
		<set name="stackable" val="true" />
		<set name="tradeable" val="false" />
		<set name="price" val="170000" />
		<set name="dropable" val="false" />
	</etcitem>
	<etcitem id="7977" name="Mercenary Posting Ticket (Wizard/Stationary)" type="SCROLL">
		<!--Done By Ragnarok (c)L2Open-Team-->
		<!--LastChange: 10.01.2011-23:26-->
		<set name="icon" val="icon.mticket_wizard_fix_i00" />
		<set name="stackable" val="true" />
		<set name="tradeable" val="false" />
		<set name="price" val="170000" />
		<set name="dropable" val="false" />
	</etcitem>
	<etcitem id="7978" name="Mercenary Posting Ticket (Sword/Mobile)" type="SCROLL">
		<!--Done By Ragnarok (c)L2Open-Team-->
		<!--LastChange: 10.01.2011-23:26-->
		<set name="icon" val="icon.mticket_sword_move_i00" />
		<set name="stackable" val="true" />
		<set name="tradeable" val="false" />
		<set name="price" val="50000" />
		<set name="dropable" val="false" />
	</etcitem>
	<etcitem id="7979" name="Mercenary Posting Ticket (Spear/Mobile)" type="SCROLL">
		<!--Done By Ragnarok (c)L2Open-Team-->
		<!--LastChange: 10.01.2011-23:26-->
		<set name="icon" val="icon.mticket_pole_move_i00" />
		<set name="stackable" val="true" />
		<set name="tradeable" val="false" />
		<set name="price" val="60000" />
		<set name="dropable" val="false" />
	</etcitem>
	<etcitem id="7980" name="Mercenary Posting Ticket (Bow/Mobile)" type="SCROLL">
		<!--Done By Ragnarok (c)L2Open-Team-->
		<!--LastChange: 10.01.2011-23:26-->
		<set name="icon" val="icon.mticket_bow_move_i00" />
		<set name="stackable" val="true" />
		<set name="tradeable" val="false" />
		<set name="price" val="70000" />
		<set name="dropable" val="false" />
	</etcitem>
	<etcitem id="7981" name="Mercenary Posting Ticket (Cleric/Mobile)" type="SCROLL">
		<!--Done By Ragnarok (c)L2Open-Team-->
		<!--LastChange: 10.01.2011-23:26-->
		<set name="icon" val="icon.mticket_cleric_move_i00" />
		<set name="stackable" val="true" />
		<set name="tradeable" val="false" />
		<set name="price" val="170000" />
		<set name="dropable" val="false" />
	</etcitem>
	<etcitem id="7982" name="Mercenary Posting Ticket (Wizard/Mobile)" type="SCROLL">
		<!--Done By Ragnarok (c)L2Open-Team-->
		<!--LastChange: 10.01.2011-23:26-->
		<set name="icon" val="icon.mticket_wizard_move_i00" />
		<set name="stackable" val="true" />
		<set name="tradeable" val="false" />
		<set name="price" val="170000" />
		<set name="dropable" val="false" />
	</etcitem>
	<etcitem id="7983" name="Mercenary Posting Ticket (Teleporter1)" type="SCROLL">
		<!--Done By Ragnarok (c)L2Open-Team-->
		<!--LastChange: 10.01.2011-23:26-->
		<set name="icon" val="icon.mticket_teleporter_fix_i00" />
		<set name="stackable" val="true" />
		<set name="tradeable" val="false" />
		<set name="price" val="100000" />
		<set name="dropable" val="false" />
	</etcitem>
	<etcitem id="7984" name="Mercenary Posting Ticket (Teleporter2)" type="SCROLL">
		<!--Done By Ragnarok (c)L2Open-Team-->
		<!--LastChange: 10.01.2011-23:26-->
		<set name="icon" val="icon.mticket_teleporter_fix_i00" />
		<set name="stackable" val="true" />
		<set name="tradeable" val="false" />
		<set name="price" val="100000" />
		<set name="dropable" val="false" />
	</etcitem>
	<etcitem id="7985" name="Mercenary Posting Ticket (Teleporter3)" type="SCROLL">
		<!--Done By Ragnarok (c)L2Open-Team-->
		<!--LastChange: 10.01.2011-23:26-->
		<set name="icon" val="icon.mticket_teleporter_fix_i00" />
		<set name="stackable" val="true" />
		<set name="tradeable" val="false" />
		<set name="price" val="100000" />
		<set name="dropable" val="false" />
	</etcitem>
	<etcitem id="7986" name="Mercenary Posting Ticket (Teleporter4)" type="SCROLL">
		<!--Done By Ragnarok (c)L2Open-Team-->
		<!--LastChange: 10.01.2011-23:26-->
		<set name="icon" val="icon.mticket_teleporter_fix_i00" />
		<set name="stackable" val="true" />
		<set name="tradeable" val="false" />
		<set name="price" val="100000" />
		<set name="dropable" val="false" />
	</etcitem>
	<etcitem id="7987" name="Mercenary Posting Ticket (Teleporter5)" type="SCROLL">
		<!--Done By Ragnarok (c)L2Open-Team-->
		<!--LastChange: 10.01.2011-23:26-->
		<set name="icon" val="icon.mticket_teleporter_fix_i00" />
		<set name="stackable" val="true" />
		<set name="tradeable" val="false" />
		<set name="price" val="100000" />
		<set name="dropable" val="false" />
	</etcitem>
	<etcitem id="7988" name="Greater Mercenary Posting Ticket (Sword/Stationary)" type="SCROLL">
		<!--Done By Ragnarok (c)L2Open-Team-->
		<!--LastChange: 10.01.2011-23:26-->
		<set name="icon" val="icon.mticket_sword_fix_i00" />
		<set name="stackable" val="true" />
		<set name="tradeable" val="false" />
		<set name="price" val="120000" />
		<set name="dropable" val="false" />
	</etcitem>
	<etcitem id="7989" name="Greater Mercenary Posting Ticket (Spear/Stationary)" type="SCROLL">
		<!--Done By Ragnarok (c)L2Open-Team-->
		<!--LastChange: 10.01.2011-23:26-->
		<set name="icon" val="icon.mticket_pole_fix_i00" />
		<set name="stackable" val="true" />
		<set name="tradeable" val="false" />
		<set name="price" val="250000" />
		<set name="dropable" val="false" />
	</etcitem>
	<etcitem id="7990" name="Greater Mercenary Posting Ticket (Bow/Stationary)" type="SCROLL">
		<!--Done By Ragnarok (c)L2Open-Team-->
		<!--LastChange: 10.01.2011-23:26-->
		<set name="icon" val="icon.mticket_bow_fix_i00" />
		<set name="stackable" val="true" />
		<set name="tradeable" val="false" />
		<set name="price" val="250000" />
		<set name="dropable" val="false" />
	</etcitem>
	<etcitem id="7991" name="Greater Mercenary Posting Ticket (Cleric/Stationary)" type="SCROLL">
		<!--Done By Ragnarok (c)L2Open-Team-->
		<!--LastChange: 10.01.2011-23:26-->
		<set name="icon" val="icon.mticket_cleric_fix_i00" />
		<set name="stackable" val="true" />
		<set name="tradeable" val="false" />
		<set name="price" val="80000" />
		<set name="dropable" val="false" />
	</etcitem>
	<etcitem id="7992" name="Greater Mercenary Posting Ticket (Wizard/Stationary)" type="SCROLL">
		<!--Done By Ragnarok (c)L2Open-Team-->
		<!--LastChange: 10.01.2011-23:26-->
		<set name="icon" val="icon.mticket_wizard_fix_i00" />
		<set name="stackable" val="true" />
		<set name="tradeable" val="false" />
		<set name="price" val="100000" />
		<set name="dropable" val="false" />
	</etcitem>
	<etcitem id="7993" name="Greater Mercenary Posting Ticket (Sword/Mobile)" type="SCROLL">
		<!--Done By Ragnarok (c)L2Open-Team-->
		<!--LastChange: 10.01.2011-23:26-->
		<set name="icon" val="icon.mticket_sword_move_i00" />
		<set name="stackable" val="true" />
		<set name="tradeable" val="false" />
		<set name="price" val="120000" />
		<set name="dropable" val="false" />
	</etcitem>
	<etcitem id="7994" name="Greater Mercenary Posting Ticket (Spear/Mobile)" type="SCROLL">
		<!--Done By Ragnarok (c)L2Open-Team-->
		<!--LastChange: 10.01.2011-23:26-->
		<set name="icon" val="icon.mticket_pole_move_i00" />
		<set name="stackable" val="true" />
		<set name="tradeable" val="false" />
		<set name="price" val="250000" />
		<set name="dropable" val="false" />
	</etcitem>
	<etcitem id="7995" name="Greater Mercenary Posting Ticket (Bow/Mobile)" type="SCROLL">
		<!--Done By Ragnarok (c)L2Open-Team-->
		<!--LastChange: 10.01.2011-23:26-->
		<set name="icon" val="icon.mticket_bow_move_i00" />
		<set name="stackable" val="true" />
		<set name="tradeable" val="false" />
		<set name="price" val="250000" />
		<set name="dropable" val="false" />
	</etcitem>
	<etcitem id="7996" name="Greater Mercenary Posting Ticket (Cleric/Mobile)" type="SCROLL">
		<!--Done By Ragnarok (c)L2Open-Team-->
		<!--LastChange: 10.01.2011-23:26-->
		<set name="icon" val="icon.mticket_cleric_move_i00" />
		<set name="stackable" val="true" />
		<set name="tradeable" val="false" />
		<set name="price" val="140000" />
		<set name="dropable" val="false" />
	</etcitem>
	<etcitem id="7997" name="Greater Mercenary Posting Ticket (Wizard/Mobile)" type="SCROLL">
		<!--Done By Ragnarok (c)L2Open-Team-->
		<!--LastChange: 10.01.2011-23:26-->
		<set name="icon" val="icon.mticket_wizard_move_i00" />
		<set name="stackable" val="true" />
		<set name="tradeable" val="false" />
		<set name="price" val="170000" />
		<set name="dropable" val="false" />
	</etcitem>
	<etcitem id="7998" name="Dawn Mercenary Posting Ticket (Sword/Stationary)" type="SCROLL">
		<!--Done By Ragnarok (c)L2Open-Team-->
		<!--LastChange: 10.01.2011-23:26-->
		<set name="icon" val="icon.mticket_sword_fix_i00" />
		<set name="stackable" val="true" />
		<set name="tradeable" val="false" />
		<set name="price" val="200000" />
		<set name="dropable" val="false" />
	</etcitem>
	<etcitem id="7999" name="Dawn Mercenary Posting Ticket (Spear/Stationary)" type="SCROLL">
		<!--Done By Ragnarok (c)L2Open-Team-->
		<!--LastChange: 10.01.2011-23:26-->
		<set name="icon" val="icon.mticket_pole_fix_i00" />
		<set name="stackable" val="true" />
		<set name="tradeable" val="false" />
		<set name="price" val="350000" />
		<set name="dropable" val="false" />
	</etcitem>
</list>
