<?xml version="1.0" encoding="UTF-8"?>

<list>
	<weapon id="3026" name="Talins Spear" type="POLE">
		<!--Done By Ragnarok (c)L2Open-Team-->
		<!--LastChange: 19.01.2011-21:47-->
		<set name="bodypart" val="LRHAND" />
		<set name="icon" val="icon.weapon_short_spear_i00" />
		<set name="weight" val="800" />
		<set name="soulshots" val="2" />
		<set name="spiritshots" val="2" />
		<set name="p_dam" val="24" />
		<set name="m_dam" val="17" />
		<set name="atk_speed" val="325" />
		<set name="rnd_dam" val="10" />
		<set name="critical" val="8" />
		<set name="tradeable" val="false" />
		<set name="price" val="105000" />
		<set name="dropable" val="false" />
	</weapon>
	<weapon id="3027" name="Old Knight's Sword" type="BIGSWORD">
		<!--Done By Ragnarok (c)L2Open-Team-->
		<!--LastChange: 19.01.2011-21:47-->
		<set name="bodypart" val="LRHAND" />
		<set name="icon" val="icon.weapon_brandish_i00" />
		<set name="weight" val="2100" />
		<set name="soulshots" val="2" />
		<set name="spiritshots" val="2" />
		<set name="p_dam" val="29" />
		<set name="m_dam" val="17" />
		<set name="atk_speed" val="325" />
		<set name="rnd_dam" val="10" />
		<set name="critical" val="8" />
		<set name="tradeable" val="false" />
		<set name="price" val="105000" />
		<set name="dropable" val="false" />
	</weapon>
	<weapon id="3028" name="Crescent Moon Bow" type="BOW">
		<!--Done By Ragnarok (c)L2Open-Team-->
		<!--LastChange: 19.01.2011-21:47-->
		<set name="bodypart" val="LRHAND" />
		<set name="icon" val="icon.weapon_short_bow_i00" />
		<set name="weight" val="600" />
		<set name="soulshots" val="6" />
		<set name="spiritshots" val="2" />
		<set name="p_dam" val="34" />
		<set name="m_dam" val="12" />
		<set name="atk_speed" val="293" />
		<set name="rnd_dam" val="5" />
		<set name="critical" val="12" />
		<set name="mp_consume" val="1" />
		<set name="tradeable" val="false" />
		<set name="price" val="41600" />
		<set name="dropable" val="false" />
	</weapon>
	<weapon id="3029" name="Sword of Binding" type="SWORD">
		<!--Done By Ragnarok (c)L2Open-Team-->
		<!--LastChange: 19.01.2011-21:47-->
		<set name="bodypart" val="RHAND" />
		<set name="icon" val="icon.weapon_gladius_i00" />
		<set name="weight" val="1200" />
		<set name="soulshots" val="2" />
		<set name="spiritshots" val="2" />
		<set name="p_dam" val="17" />
		<set name="m_dam" val="12" />
		<set name="atk_speed" val="379" />
		<set name="rnd_dam" val="10" />
		<set name="critical" val="8" />
		<set name="tradeable" val="false" />
		<set name="price" val="41600" />
		<set name="dropable" val="false" />
	</weapon>
</list>
